di_plugins/__init__.py
di_plugins/callbacks/__init__.py
di_plugins/callbacks/di_failure_callback.py
di_plugins/callbacks/di_success_callback.py
di_plugins/callbacks/execution_summary_callback.py
di_plugins/callbacks/failure_callback.py
di_plugins/callbacks/sdk_external_callbacks.py
di_plugins/callbacks/sla_miss_callback.py
di_plugins/callbacks/success_callback.py
di_plugins/hooks/__init__.py
di_plugins/hooks/vault_hook.py
di_plugins/operators/__init__.py
di_plugins/operators/acquire_lock_sensor_operator.py
di_plugins/operators/acquire_multiple_lock_sensor_operator.py
di_plugins/operators/bash_operator.py
di_plugins/operators/branch_python_operator.py
di_plugins/operators/di_external_task_sensor_operator.py
di_plugins/operators/email_operator.py
di_plugins/operators/hdfs_file_sensor_operator.py
di_plugins/operators/job_monitoring_sensor_operator.py
di_plugins/operators/local_file_sensor_operator.py
di_plugins/operators/operator_service.py
di_plugins/operators/oracle_operator.py
di_plugins/operators/python_operator.py
di_plugins/operators/short_circuit_python_operator.py
di_plugins/operators/spark_operator.py
di_plugins/operators/ssh_operator.py
di_plugins/operators/trigger_dag_run_operator.py
di_plugins/resources/__init__.py
di_plugins/resources/log_config.yaml
di_plugins/sensors/__init__.py
di_plugins/sensors/acquire_lock_sensor.py
di_plugins/sensors/acquire_multiple_lock_sensor.py
di_plugins/sensors/di_external_task_sensor.py
di_plugins/sensors/hdfs_sensor.py
di_plugins/sensors/job_monitor_sensor.py
di_plugins/sensors/local_file_sensor.py
di_plugins/sensors/sensor_util.py
di_plugins/sensors/ssh_sensor.py
di_plugins/utils/__init__.py
di_plugins/utils/util.py
airtel_airflow_plugins-1.5.0.dist-info/LICENSE
airtel_airflow_plugins-1.5.0.dist-info/METADATA
airtel_airflow_plugins-1.5.0.dist-info/WHEEL
airtel_airflow_plugins-1.5.0.dist-info/entry_points.txt
airtel_airflow_plugins-1.5.0.dist-info/top_level.txt
airtel_airflow_plugins-1.5.0.dist-info/RECORD
