Metadata-Version: 2.1
Name: airtel-airflow-plugins
Version: 1.5.0
Summary: DARTS airflow plugins containing custom operators, sensors, callbacks and hooks
Home-page: https://code.airtelworld.in:7990/bitbucket/scm/sr/darts-airflow-plugins.git
Author: Ashutosh, Ankita, Deepak
Author-email: ashutosh1.joshi@airtel.com, ankita1.verma@airtel.com, deepak.lamba@airtel.com
License: UNKNOWN
Keywords: airflow,scheduler
Platform: UNKNOWN
Classifier: Development Status :: 3 - Alpha
Classifier: Intended Audience :: Developers
Classifier: License :: OSI Approved :: MIT License 
Classifier: Natural Language :: English
Classifier: Operating System :: OS Independent
Classifier: Programming Language :: Python :: 3
Requires-Python: >=3.7
Requires-Dist: apache-airflow (==2.3.2)
Requires-Dist: apache-airflow-providers-hashicorp (==2.2.0)
Requires-Dist: apache-airflow-providers-oracle (==2.2.3)
Requires-Dist: apache-airflow-providers-ssh (==2.4.4)
